pychancalculator/__init__.py
pychancalculator/calculator.py
py_chan_calculator-0.0.1.dist-info/LICENSE
py_chan_calculator-0.0.1.dist-info/METADATA
py_chan_calculator-0.0.1.dist-info/WHEEL
py_chan_calculator-0.0.1.dist-info/top_level.txt
py_chan_calculator-0.0.1.dist-info/RECORD
